setup.py
Flask_RESTful_Fieldsets.egg-info/PKG-INFO
Flask_RESTful_Fieldsets.egg-info/SOURCES.txt
Flask_RESTful_Fieldsets.egg-info/dependency_links.txt
Flask_RESTful_Fieldsets.egg-info/not-zip-safe
Flask_RESTful_Fieldsets.egg-info/requires.txt
Flask_RESTful_Fieldsets.egg-info/top_level.txt
flask_restful_fieldsets/__init__.py
flask_restful_fieldsets/fields.py
flask_restful_fieldsets/fieldset.py
tests/__init__.py
tests/test_fields.py
tests/test_fieldset.py