Metadata-Version: 1.0
Name: Flask-RESTful-Fieldsets
Version: 0.1.0
Summary: Extension to Flask-RESTful to create fieldsets
Home-page: https://www.github.com/janlo/flask-restful-fieldsets/
Author: Jan Losinski
Author-email: UNKNOWN
License: UNKNOWN
Platform: any
